Workbook

Sheet Home
B2: =Settings!B4 -> [Your Business Name]
B3: =Settings!B6 -> Virtual Assistant · Technical Support · Content & Video Editing
B5: VA BUSINESS SUITE · v2.0
B9: GO TO
B11: 📊 Dashboard | D11: ⏱ Timesheet | F11: 🧾 Invoice
B12: Live KPIs & charts | D12: Log hours | F12: Bill clients
B13: Open → | D13: Open → | F13: Open →
B16: 💰 Bookkeeping | D16: 👥 Client CRM | F16: ✅ Task Tracker
B17: Income & expenses | D17: Contacts & rates | F17: Deadlines & status
B18: Open → | D18: Open → | F18: Open →
B21: 📅 Content Calendar | D21: ⚙ Settings
B22: Social planning | D22: Business info
B23: Open → | D23: Open →
B26: Tip: update Settings once and your business name/rate flow through automatically. Click any tile to jump straight there.

Sheet Dashboard
A1: Business Dashboard
A2: Live overview — pulls automatically from Timesheet, Bookkeeping, and Task Tracker.
A5: TOTAL HOURS LOGGED | C5: TOTAL BILLED | E5: TOTAL INCOME | G5: TOTAL EXPENSES | I5: NET PROFIT | K5: CASH BALANCE
A6: =Timesheet!F37 -> 3 | C6: =Timesheet!H37 -> 45 | E6: =SUMIF(Bookkeeping!E6:E45,"Income",Bookkeeping!F6:F45) -> 650 | G6: =SUMIF(Bookkeeping!E6:E45,"Expense",Bookkeeping!F6:F45) -> 630 | I6: =D5-D6 -> 0 | K6: =Bookkeeping!G45
A9: Hours by Client (edit client names below to match your Timesheet)
A10: Client | B10: Hours
A11: Acme Corp | B11: =SUMIF(Timesheet!$B$6:$B$35,A11,Timesheet!$F$6:$F$35) -> 3
A12: Client 2 | B12: =SUMIF(Timesheet!$B$6:$B$35,A12,Timesheet!$F$6:$F$35) -> 0
A13: Client 3 | B13: =SUMIF(Timesheet!$B$6:$B$35,A13,Timesheet!$F$6:$F$35) -> 0
A14: Client 4 | B14: =SUMIF(Timesheet!$B$6:$B$35,A14,Timesheet!$F$6:$F$35) -> 0
A15: Client 5 | B15: =SUMIF(Timesheet!$B$6:$B$35,A15,Timesheet!$F$6:$F$35) -> 0
A18: Income vs Expense by Category
A29: Task Status Breakdown
A38: Client Snapshot
A39: Select a client: | B39: Acme Corp
A41: Hours Logged | B41: =SUMIF(Timesheet!$B$6:$B$35,$B$39,Timesheet!$F$6:$F$35) -> 3
A42: Total Billed | B42: =SUMIF(Timesheet!$B$6:$B$35,$B$39,Timesheet!$H$6:$H$35) -> 45
A43: Open Tasks | B43: =COUNTIFS('Task Tracker'!$A$6:$A$40,$B$39,'Task Tracker'!$D$6:$D$40,"<>Done") -> 1
A44: Overdue Tasks | B44: =COUNTIFS('Task Tracker'!$A$6:$A$40,$B$39,'Task Tracker'!$E$6:$E$40,"<"&TODAY(),'Task Tracker'!$D$6:$D$40,"<>Done") -> 0
A46: Legend: gold cells (client names) are editable — update them to match your actual Timesheet client names for the chart to reflect your data.

Sheet Timesheet
A1: Time Sheet
A2: Log hours per client/task — Total calculates automatically.
A5: Date | B5: Client | C5: Task / Description | D5: Start Time | E5: End Time | F5: Hours | G5: Hourly Rate ($) | H5: Total ($)
A6: 2026-07-01 | B6: Acme Corp | C6: Inbox management & scheduling | D6: 09:00 | E6: 12:00 | F6: =(E6-D6)*24 -> 3 | G6: 15 | H6: =F6*G6 -> 45
F7: =IF(D7="","",(E7-D7)*24) | H7: =IF(F7="","",F7*G7)
F8: =IF(D8="","",(E8-D8)*24) | H8: =IF(F8="","",F8*G8)
F9: =IF(D9="","",(E9-D9)*24) | H9: =IF(F9="","",F9*G9)
F10: =IF(D10="","",(E10-D10)*24) | H10: =IF(F10="","",F10*G10)
F11: =IF(D11="","",(E11-D11)*24) | H11: =IF(F11="","",F11*G11)
F12: =IF(D12="","",(E12-D12)*24) | H12: =IF(F12="","",F12*G12)
F13: =IF(D13="","",(E13-D13)*24) | H13: =IF(F13="","",F13*G13)
F14: =IF(D14="","",(E14-D14)*24) | H14: =IF(F14="","",F14*G14)
F15: =IF(D15="","",(E15-D15)*24) | H15: =IF(F15="","",F15*G15)
F16: =IF(D16="","",(E16-D16)*24) | H16: =IF(F16="","",F16*G16)
F17: =IF(D17="","",(E17-D17)*24) | H17: =IF(F17="","",F17*G17)
F18: =IF(D18="","",(E18-D18)*24) | H18: =IF(F18="","",F18*G18)
... F35: =IF(D35="","",(E35-D35)*24) | H35: =IF(F35="","",F35*G35)
A37: TOTAL | F37: =SUM(F6:F35) -> 3 | H37: =SUM(H6:H35) -> 45
A39: Legend: gold cells = enter your data. Row 6 is an example — replace or delete it.

Sheet Invoice
A1: INVOICE | F1: Invoice #: | G1: Invoice #: | H1: =Settings!B8&"0001" -> INV-0001 | I1: Status: | J1: Unpaid
A2: =Settings!B4&" — "&Settings!B6 -> [Your Business Name] — Virtual Assistant · Technical Support · Content & Video Editing | F2: Date: | G2: 2026-07-01
F3: Due Date: | G3: 2026-07-15
A5: Bill To:
A6: Client Name
A7: Client Company
A8: Client Email
A10: Date | B10: Description | C10: Hours | D10: Rate ($) | E10: Amount ($)
A11: 2026-07-01 | B11: Inbox management & scheduling | C11: 10 | D11: 15 | E11: =C11*D11 -> 150
E12: =IF(C12="","",C12*D12)
E13: =IF(C13="","",C13*D13)
E14: =IF(C14="","",C14*D14)
E15: =IF(C15="","",C15*D15)
E16: =IF(C16="","",C16*D16)
E17: =IF(C17="","",C17*D17)
E18: =IF(C18="","",C18*D18)
E19: =IF(C19="","",C19*D19)
E20: =IF(C20="","",C20*D20)
B22: Subtotal | E22: =SUM(E11:E20) -> 150
B23: Discount (%) | C23: 0 | E23: =E22*C23 -> 0
B24: TOTAL DUE | E24: =E22-E23 -> 150
A26: Payment Details:
A27: PayPal / Payoneer / Bank details go here
A29: Thank you for your business!
A31: Legend: gold cells = enter your data. Row 11 is an example. Amount & totals calculate automatically.

Sheet Bookkeeping
A1: Income & Expense Tracker
A2: Log every transaction — running balance calculates automatically.
A5: Date | B5: Description | C5: Client / Source | D5: Category | E5: Type | F5: Amount ($) | G5: Running Balance ($)
A6: 2026-07-01 | B6: June invoice payment | C6: Acme Corp | D6: Client Payment | E6: Income | F6: 450 | G6: =F6 -> 450
D7: Client Payment | E7: Income | F7: 200 | G7: =IF(F7="","",G6+IF(E7="Expense",-F7,F7)) -> 650
A8: 46214 | D8: Internet/Phone | E8: Expense | F8: 630 | G8: =IF(F8="","",G7+IF(E8="Expense",-F8,F8)) -> 20
G9: =IF(F9="","",G8+IF(E9="Expense",-F9,F9))
G10: =IF(F10="","",G9+IF(E10="Expense",-F10,F10))
G11: =IF(F11="","",G10+IF(E11="Expense",-F11,F11))
G12: =IF(F12="","",G11+IF(E12="Expense",-F12,F12))
G13: =IF(F13="","",G12+IF(E13="Expense",-F13,F13))
G14: =IF(F14="","",G13+IF(E14="Expense",-F14,F14))
G15: =IF(F15="","",G14+IF(E15="Expense",-F15,F15))
G16: =IF(F16="","",G15+IF(E16="Expense",-F16,F16))
G17: =IF(F17="","",G16+IF(E17="Expense",-F17,F17))
G18: =IF(F18="","",G17+IF(E18="Expense",-F18,F18))
G19: =IF(F19="","",G18+IF(E19="Expense",-F19,F19))
G20: =IF(F20="","",G19+IF(E20="Expense",-F20,F20))
... G45: =IF(F45="","",G44+IF(E45="Expense",-F45,F45))
A48: Category Summary
A49: Category | B49: Income ($) | C49: Expense ($)
A50: Client Payment | B50: =SUMIFS($F$6:$F$45,$D$6:$D$45,A50,$E$6:$E$45,"Income") -> 650 | C50: =SUMIFS($F$6:$F$45,$D$6:$D$45,A50,$E$6:$E$45,"Expense") -> 0
A51: Software/Tools | B51: =SUMIFS($F$6:$F$45,$D$6:$D$45,A51,$E$6:$E$45,"Income") -> 0 | C51: =SUMIFS($F$6:$F$45,$D$6:$D$45,A51,$E$6:$E$45,"Expense") -> 0
A52: Internet/Phone | B52: =SUMIFS($F$6:$F$45,$D$6:$D$45,A52,$E$6:$E$45,"Income") -> 0 | C52: =SUMIFS($F$6:$F$45,$D$6:$D$45,A52,$E$6:$E$45,"Expense") -> 630
A53: Equipment | B53: =SUMIFS($F$6:$F$45,$D$6:$D$45,A53,$E$6:$E$45,"Income") -> 0 | C53: =SUMIFS($F$6:$F$45,$D$6:$D$45,A53,$E$6:$E$45,"Expense") -> 0
A54: Training | B54: =SUMIFS($F$6:$F$45,$D$6:$D$45,A54,$E$6:$E$45,"Income") -> 0 | C54: =SUMIFS($F$6:$F$45,$D$6:$D$45,A54,$E$6:$E$45,"Expense") -> 0
A55: Marketing | B55: =SUMIFS($F$6:$F$45,$D$6:$D$45,A55,$E$6:$E$45,"Income") -> 0 | C55: =SUMIFS($F$6:$F$45,$D$6:$D$45,A55,$E$6:$E$45,"Expense") -> 0
A56: Taxes | B56: =SUMIFS($F$6:$F$45,$D$6:$D$45,A56,$E$6:$E$45,"Income") -> 0 | C56: =SUMIFS($F$6:$F$45,$D$6:$D$45,A56,$E$6:$E$45,"Expense") -> 0
A57: Other | B57: =SUMIFS($F$6:$F$45,$D$6:$D$45,A57,$E$6:$E$45,"Income") -> 0 | C57: =SUMIFS($F$6:$F$45,$D$6:$D$45,A57,$E$6:$E$45,"Expense") -> 0
A59: Legend: gold cells = enter your data. Row 6 is an example. Category Summary feeds the Dashboard charts.
A60: Monthly Trend (edit month labels to match your data)
A61: Month | B61: Income ($) | C61: Expense ($)
A62: Jul 2026 | B62: =SUMPRODUCT((TEXT($A$6:$A$45,"mmm yyyy")=A62)*($E$6:$E$45="Income")*$F$6:$F$45) -> 450 | C62: =SUMPRODUCT((TEXT($A$6:$A$45,"mmm yyyy")=A62)*($E$6:$E$45="Expense")*$F$6:$F$45) -> 630
A63: Aug 2026 | B63: =SUMPRODUCT((TEXT($A$6:$A$45,"mmm yyyy")=A63)*($E$6:$E$45="Income")*$F$6:$F$45) -> 0 | C63: =SUMPRODUCT((TEXT($A$6:$A$45,"mmm yyyy")=A63)*($E$6:$E$45="Expense")*$F$6:$F$45) -> 0
A64: Sep 2026 | B64: =SUMPRODUCT((TEXT($A$6:$A$45,"mmm yyyy")=A64)*($E$6:$E$45="Income")*$F$6:$F$45) -> 0 | C64: =SUMPRODUCT((TEXT($A$6:$A$45,"mmm yyyy")=A64)*($E$6:$E$45="Expense")*$F$6:$F$45) -> 0
A65: Oct 2026 | B65: =SUMPRODUCT((TEXT($A$6:$A$45,"mmm yyyy")=A65)*($E$6:$E$45="Income")*$F$6:$F$45) -> 0 | C65: =SUMPRODUCT((TEXT($A$6:$A$45,"mmm yyyy")=A65)*($E$6:$E$45="Expense")*$F$6:$F$45) -> 0
A66: Nov 2026 | B66: =SUMPRODUCT((TEXT($A$6:$A$45,"mmm yyyy")=A66)*($E$6:$E$45="Income")*$F$6:$F$45) -> 0 | C66: =SUMPRODUCT((TEXT($A$6:$A$45,"mmm yyyy")=A66)*($E$6:$E$45="Expense")*$F$6:$F$45) -> 0
A67: Dec 2026 | B67: =SUMPRODUCT((TEXT($A$6:$A$45,"mmm yyyy")=A67)*($E$6:$E$45="Income")*$F$6:$F$45) -> 0 | C67: =SUMPRODUCT((TEXT($A$6:$A$45,"mmm yyyy")=A67)*($E$6:$E$45="Expense")*$F$6:$F$45) -> 0

Sheet Client CRM
A1: Client Contact & CRM Sheet
A2: Track client details, platform, rate, and contract status.
A5: Client Name | B5: Company | C5: Platform | D5: Contact Email | E5: Hourly Rate ($) | F5: Contract Start | G5: Contract End | H5: Notes
A6: Jane Smith | B6: Acme Corp | C6: Upwork | D6: jane@example.com | E6: 15 | F6: 2026-01-01 | G6: Ongoing | H6: Prefers weekly check-in calls
A42: Legend: gold cells = enter your data. Row 6 is an example. Platform has a dropdown.

Sheet Task Tracker
A1: Task & Project Tracker
A2: Track tasks per client from To Do through Done. Overdue tasks auto-highlight.
A5: Client | B5: Task | C5: Priority | D5: Status | E5: Due Date | F5: Assigned Date | G5: Notes | I5: Priority Level
A6: Acme Corp | B6: Edit July promo video | C6: High | D6: In Progress | E6: 2026-07-10 | F6: 2026-07-01 | G6: Client sent raw footage via Drive | I6: =IFERROR(MATCH($C6,{"Low","Medium","High","Urgent"},0),"") -> 3
I7: =IFERROR(MATCH($C7,{"Low","Medium","High","Urgent"},0),"")
I8: =IFERROR(MATCH($C8,{"Low","Medium","High","Urgent"},0),"")
I9: =IFERROR(MATCH($C9,{"Low","Medium","High","Urgent"},0),"")
I10: =IFERROR(MATCH($C10,{"Low","Medium","High","Urgent"},0),"")
I11: =IFERROR(MATCH($C11,{"Low","Medium","High","Urgent"},0),"")
I12: =IFERROR(MATCH($C12,{"Low","Medium","High","Urgent"},0),"")
I13: =IFERROR(MATCH($C13,{"Low","Medium","High","Urgent"},0),"")
I14: =IFERROR(MATCH($C14,{"Low","Medium","High","Urgent"},0),"")
I15: =IFERROR(MATCH($C15,{"Low","Medium","High","Urgent"},0),"")
I16: =IFERROR(MATCH($C16,{"Low","Medium","High","Urgent"},0),"")
I17: =IFERROR(MATCH($C17,{"Low","Medium","High","Urgent"},0),"")
I18: =IFERROR(MATCH($C18,{"Low","Medium","High","Urgent"},0),"")
... I40: =IFERROR(MATCH($C40,{"Low","Medium","High","Urgent"},0),"")
A43: Status Summary
A44: To Do | B44: =COUNTIF($D$6:$D$40,"To Do") -> 0
A45: In Progress | B45: =COUNTIF($D$6:$D$40,"In Progress") -> 1
A46: Waiting on Client | B46: =COUNTIF($D$6:$D$40,"Waiting on Client") -> 0
A47: Done | B47: =COUNTIF($D$6:$D$40,"Done") -> 0
A49: Priority Level column powers the traffic-light indicator (1=Low … 4=Urgent). Leave it as-is.

Sheet Content Calendar
A1: Social Media Content Calendar
A2: Plan posts by date, platform, and status.
A5: Date | B5: Client | C5: Platform | D5: Content Type | E5: Caption / Topic | F5: Status | G5: Post Time | H5: Notes
A6: 2026-07-01 | B6: Acme Corp | C6: Instagram | D6: Reel | E6: Behind-the-scenes clip | F6: Scheduled | G6: 10:00 | H6: Use trending audio
A42: Legend: gold cells = enter your data. Row 6 is an example. Platform & Status have dropdowns.

Sheet Settings
A1: Settings
A2: Edit these once — they automatically update your Home page and Invoice.
A4: Business Name | B4: [Your Business Name]
A5: Your Name | B5: Luis Andrei Abarquez
A6: Tagline | B6: Virtual Assistant · Technical Support · Content & Video Editing
A7: Default Hourly Rate ($) | B7: 15
A8: Invoice Prefix | B8: INV-
A9: Currency Symbol | B9: $
