Workbook

Sheet Timesheet
A1: VA Time Sheet
A2: Log hours per client/task. Rate and Total calculate automatically.
A4: Date | B4: Client | C4: Task / Description | D4: Start Time | E4: End Time | F4: Hours | G4: Hourly Rate ($) | H4: Total ($)
A5: 2026-07-01 | B5: Acme Corp | C5: Inbox management & scheduling | D5: 09:00 | E5: 12:00 | F5: =(E5-D5)*24 -> 3 | G5: 15 | H5: =F5*G5 -> 45
F6: =IF(D6="","",(E6-D6)*24) | H6: =IF(F6="","",F6*G6)
F7: =IF(D7="","",(E7-D7)*24) | H7: =IF(F7="","",F7*G7)
F8: =IF(D8="","",(E8-D8)*24) | H8: =IF(F8="","",F8*G8)
F9: =IF(D9="","",(E9-D9)*24) | H9: =IF(F9="","",F9*G9)
F10: =IF(D10="","",(E10-D10)*24) | H10: =IF(F10="","",F10*G10)
F11: =IF(D11="","",(E11-D11)*24) | H11: =IF(F11="","",F11*G11)
F12: =IF(D12="","",(E12-D12)*24) | H12: =IF(F12="","",F12*G12)
F13: =IF(D13="","",(E13-D13)*24) | H13: =IF(F13="","",F13*G13)
F14: =IF(D14="","",(E14-D14)*24) | H14: =IF(F14="","",F14*G14)
F15: =IF(D15="","",(E15-D15)*24) | H15: =IF(F15="","",F15*G15)
F16: =IF(D16="","",(E16-D16)*24) | H16: =IF(F16="","",F16*G16)
F17: =IF(D17="","",(E17-D17)*24) | H17: =IF(F17="","",F17*G17)
... F34: =IF(D34="","",(E34-D34)*24) | H34: =IF(F34="","",F34*G34)
A36: TOTAL | F36: =SUM(F5:F35) -> 3 | H36: =SUM(H5:H35) -> 45
A38: Legend: yellow cells = enter your data. Row 5 is an example — replace or delete it. Hours & Total calculate automatically.

Sheet Bookkeeping
A1: Income & Expense Tracker
A2: Log every transaction. Running balance and category totals calculate automatically.
A4: Date | B4: Description | C4: Client / Source | D4: Category | E4: Type | F4: Amount ($) | G4: Running Balance ($)
A5: 2026-07-01 | B5: June invoice payment | C5: Acme Corp | D5: Client Payment | E5: Income | F5: 450 | G5: =F5 -> 450
G6: =IF(F6="","",G5+IF(E6="Expense",-F6,F6))
G7: =IF(F7="","",G6+IF(E7="Expense",-F7,F7))
G8: =IF(F8="","",G7+IF(E8="Expense",-F8,F8))
G9: =IF(F9="","",G8+IF(E9="Expense",-F9,F9))
G10: =IF(F10="","",G9+IF(E10="Expense",-F10,F10))
G11: =IF(F11="","",G10+IF(E11="Expense",-F11,F11))
G12: =IF(F12="","",G11+IF(E12="Expense",-F12,F12))
G13: =IF(F13="","",G12+IF(E13="Expense",-F13,F13))
G14: =IF(F14="","",G13+IF(E14="Expense",-F14,F14))
G15: =IF(F15="","",G14+IF(E15="Expense",-F15,F15))
G16: =IF(F16="","",G15+IF(E16="Expense",-F16,F16))
G17: =IF(F17="","",G16+IF(E17="Expense",-F17,F17))
... G44: =IF(F44="","",G43+IF(E44="Expense",-F44,F44))
A47: Legend: yellow cells = enter your data. Row 5 is an example — replace or delete it. Type & Category have dropdowns.

Sheet Summary
A1: Monthly Summary
A2: Auto-calculated from Timesheet and Bookkeeping tabs.
A4: Metric | B4: Value | C4: Notes
A5: Total Hours Logged (Timesheet) | B5: =Timesheet!F36 -> 3 | C5: Sum of all hours in Timesheet tab
A6: Total Billed ($) | B6: =Timesheet!H36 -> 45 | C6: Sum of Total column in Timesheet tab
A7: Total Income ($) | B7: =SUMIF(Bookkeeping!E5:E44,"Income",Bookkeeping!F5:F44) -> 450 | C7: Sum of Income rows in Bookkeeping tab
A8: Total Expenses ($) | B8: =SUMIF(Bookkeeping!E5:E44,"Expense",Bookkeeping!F5:F44) -> 0 | C8: Sum of Expense rows in Bookkeeping tab
A9: Net Profit ($) | B9: =B7-B8 -> 450 | C9: Income minus Expenses
A10: Current Cash Balance ($) | B10: =Bookkeeping!G44 | C10: Last running balance value in Bookkeeping tab
A12: Tip: extend the SUMIF ranges (E5:E44 / F5:F44) if you add more rows to Bookkeeping.
